byteb4rb1e_sphinxcontrib/__init__.py
byteb4rb1e_sphinxcontrib/abc.py
byteb4rb1e_sphinxcontrib/authorship/__init__.py
byteb4rb1e_sphinxcontrib/authorship/parsers/__init__.py
byteb4rb1e_sphinxcontrib/authorship/parsers/rst/__init__.py
byteb4rb1e_sphinxcontrib/authorship/parsers/rst/directives/__init__.py
byteb4rb1e_sphinxcontrib/authorship/parsers/rst/directives/contribution.py
byteb4rb1e_sphinxcontrib/svc/__init__.py
byteb4rb1e_sphinxcontrib/svc_authorship/__init__.py
byteb4rb1e_sphinxcontrib-0.1.0.dist-info/licenses/LICENSE
byteb4rb1e_sphinxcontrib-0.1.0.dist-info/METADATA
byteb4rb1e_sphinxcontrib-0.1.0.dist-info/WHEEL
byteb4rb1e_sphinxcontrib-0.1.0.dist-info/top_level.txt
byteb4rb1e_sphinxcontrib-0.1.0.dist-info/RECORD
