Metadata-Version: 2.4
Name: byteb4rb1e.sphinxcontrib
Version: 0.1.0
Author-email: Tiara Rodney <tiara.rodney@byteb4rb1e.me>
Project-URL: Bitbucket, https://bitbucket.org/byteb4rb1e/sphinxcontrib
Classifier: Development Status :: 1 - Planning
Classifier: Environment :: Web Environment
Classifier: Framework :: Sphinx
Classifier: Framework :: Sphinx :: Extension
Classifier: Operating System :: OS Independent
Classifier: Programming Language :: Python :: 3
Classifier: Programming Language :: Python :: 3.9
Classifier: Programming Language :: Python :: 3.10
Classifier: Programming Language :: Python :: 3.11
Classifier: Programming Language :: Python :: 3.12
Classifier: Topic :: Documentation
Classifier: Topic :: Software Development :: Documentation
Requires-Python: >=3.8
License-File: LICENSE
Requires-Dist: sphinx>=5.1
Dynamic: license-file
